charmed_kubeflow_chisme/__init__.py
charmed_kubeflow_chisme/bundle/__init__.py
charmed_kubeflow_chisme/bundle/_bundle.py
charmed_kubeflow_chisme/components/__init__.py
charmed_kubeflow_chisme/components/charm_reconciler.py
charmed_kubeflow_chisme/components/component.py
charmed_kubeflow_chisme/components/component_graph.py
charmed_kubeflow_chisme/components/component_graph_item.py
charmed_kubeflow_chisme/components/kubernetes_component.py
charmed_kubeflow_chisme/components/leadership_gate_component.py
charmed_kubeflow_chisme/components/model_name_gate_component.py
charmed_kubeflow_chisme/components/pebble_component.py
charmed_kubeflow_chisme/components/sa_token_component.py
charmed_kubeflow_chisme/components/serialised_data_interface_components.py
charmed_kubeflow_chisme/exceptions/__init__.py
charmed_kubeflow_chisme/exceptions/_generic_charm_runtime_error.py
charmed_kubeflow_chisme/exceptions/_kubernetes.py
charmed_kubeflow_chisme/exceptions/_with_status.py
charmed_kubeflow_chisme/juju/__init__.py
charmed_kubeflow_chisme/juju/_juju.py
charmed_kubeflow_chisme/kubernetes/__init__.py
charmed_kubeflow_chisme/kubernetes/_check_resources.py
charmed_kubeflow_chisme/kubernetes/_kubernetes_resource_handler.py
charmed_kubeflow_chisme/kubernetes/_validate_statefulset.py
charmed_kubeflow_chisme/lightkube/__init__.py
charmed_kubeflow_chisme/lightkube/mocking.py
charmed_kubeflow_chisme/lightkube/batch/__init__.py
charmed_kubeflow_chisme/lightkube/batch/_many.py
charmed_kubeflow_chisme/lightkube/batch/_sort_objects.py
charmed_kubeflow_chisme/pebble/__init__.py
charmed_kubeflow_chisme/pebble/_update_layer.py
charmed_kubeflow_chisme/rock/__init__.py
charmed_kubeflow_chisme/rock/_check_rock.py
charmed_kubeflow_chisme/service_mesh/__init__.py
charmed_kubeflow_chisme/service_mesh/policies.py
charmed_kubeflow_chisme/status_handling/__init__.py
charmed_kubeflow_chisme/status_handling/_get_first_worst_error.py
charmed_kubeflow_chisme/status_handling/_set_and_log_status.py
charmed_kubeflow_chisme-0.4.24.dist-info/licenses/LICENSE
charmed_kubeflow_chisme-0.4.24.dist-info/METADATA
charmed_kubeflow_chisme-0.4.24.dist-info/WHEEL
charmed_kubeflow_chisme-0.4.24.dist-info/top_level.txt
charmed_kubeflow_chisme-0.4.24.dist-info/RECORD
