Metadata-Version: 2.4
Name: charmed-kubeflow-chisme
Version: 0.4.24
Summary: A collection of helpers for Charms maintained by the Charmed Kubeflow team
Home-page: https://github.com/canonical/charmed-kubeflow-chisme
Author: Charmed Kubeflow
Classifier: Programming Language :: Python :: 3
Classifier: License :: OSI Approved :: MIT License
Classifier: Operating System :: OS Independent
Requires-Python: >=3.6
License-File: LICENSE
Requires-Dist: deepdiff<=6.2.1
Requires-Dist: jinja2
Requires-Dist: lightkube>0.10.0
Requires-Dist: ops>1.2.0
Requires-Dist: serialized-data-interface
Requires-Dist: ruamel.yaml
Requires-Dist: tenacity
Requires-Dist: juju
Requires-Dist: httpx<0.28.0
Requires-Dist: kubernetes>=30.1.0
Requires-Dist: aiohttp<4.0,>=3.8
Requires-Dist: charmed-service-mesh-helpers>=0.3.0
Requires-Dist: lightkube-extensions>=0.3.0
Provides-Extra: test
Requires-Dist: pytest; extra == "test"
Requires-Dist: black; extra == "test"
Dynamic: license-file
